AVMWeather/__init__.py
AVMWeather-1.0.0.dist-info/LICENSE
AVMWeather-1.0.0.dist-info/METADATA
AVMWeather-1.0.0.dist-info/WHEEL
AVMWeather-1.0.0.dist-info/top_level.txt
AVMWeather-1.0.0.dist-info/RECORD
