Metadata-Version: 2.1
Name: AVMWeather
Version: 1.0.0
Summary: Get weather data in a simple way.
Home-page: https://github.com/avmmodules/AVMWeather
Author: AlejandroV
Author-email: avmmodules@gmail.com
Project-URL: Bug Tracker, https://github.com/avmmodules/AVMWeather/issues
Classifier: Programming Language :: Python :: 3
Classifier: License :: OSI Approved :: MIT License
Classifier: Operating System :: OS Independent
Requires-Python: >=3.6
License-File: LICENSE
